{
    "identifier": 937,
    "versioning": "https://miilucl.github.io/dcouvr/sesam_v0/profile_schema.html",
    "timestamp": "2024-01-17T17:56:40.517225",
    "preferences": {
        "categories": [
            {
                "name": "ÉVÉNEMENTS POUR ENFANTS - stages",
                "termCode": "CAT04-07",
                "inDefinedTermSet": "https://miilucl.github.io/dcouvr/sesam_v0/termSets/DefinedTermSet_categories.csv",
                "rating": 5,
                "timestamp": "2024-01-17T17:56:40.511494"
            },
            {
                "name": "ACTIVITÉS DIVERSES - portes ouvertes",
                "termCode": "CAT11-06",
                "inDefinedTermSet": "https://miilucl.github.io/dcouvr/sesam_v0/termSets/DefinedTermSet_categories.csv",
                "rating": 5,
                "timestamp": "2024-01-17T17:56:40.512526"
            }
        ],
        "audiences": [],
        "areas": [
            {
                "name": "Tournai",
                "termCode": "LOC15",
                "inDefinedTermSet": "https://miilucl.github.io/dcouvr/sesam_v0/termSets/DefinedTermSet_location.csv",
                "rating": 2,
                "timestamp": "2024-01-17T17:56:40.514486"
            },
            {
                "name": "Nivelles",
                "termCode": "LOC09",
                "inDefinedTermSet": "https://miilucl.github.io/dcouvr/sesam_v0/termSets/DefinedTermSet_location.csv",
                "rating": 2,
                "timestamp": "2024-01-17T17:56:40.514486"
            },
            {
                "name": "Thuin",
                "termCode": "LOC14",
                "inDefinedTermSet": "https://miilucl.github.io/dcouvr/sesam_v0/termSets/DefinedTermSet_location.csv",
                "rating": 4,
                "timestamp": "2024-01-17T17:56:40.515487"
            }
        ],
        "culturalProducts": [
            {
                "identifier": 10005,
                "name": "Vos livres ont la parole !",
                "type": "Event",
                "rating": 4,
                "timestamp": "2024-01-17T17:56:40.515487"
            }
        ],
        "culturalOperators": [
            {
                "identifier": 20004,
                "name": "Plaza",
                "rating": 5,
                "timestamp": "2024-01-17T17:56:40.515487"
            },
            {
                "identifier": 20001,
                "name": "Blues-sphere Bar",
                "rating": 3,
                "timestamp": "2024-01-17T17:56:40.515487"
            },
            {
                "identifier": 20006,
                "name": "Palais des Beaux-Arts de Bruxelles - Bozar",
                "rating": 5,
                "timestamp": "2024-01-17T17:56:40.515487"
            },
            {
                "identifier": 20006,
                "name": "Palais des Beaux-Arts de Bruxelles - Bozar",
                "rating": 3,
                "timestamp": "2024-01-17T17:56:40.515487"
            }
        ],
        "culturalCreators": [
            {
                "identifier": 30004,
                "name": "Damso",
                "rating": 2,
                "timestamp": "2024-01-17T17:56:40.517065"
            },
            {
                "identifier": 30001,
                "name": "Girls in Hawaii",
                "rating": 4,
                "timestamp": "2024-01-17T17:56:40.517065"
            }
        ]
    }
}